main.py
utils.py
py_dos_b1-1.1.6.data/scripts/boot.py
py_dos_b1-1.1.6.dist-info/METADATA
py_dos_b1-1.1.6.dist-info/WHEEL
py_dos_b1-1.1.6.dist-info/entry_points.txt
py_dos_b1-1.1.6.dist-info/top_level.txt
py_dos_b1-1.1.6.dist-info/RECORD
